eeg_filters/__init__.py
eeg_filters/data_importer.py
eeg_filters/export.py
eeg_filters/filters.py
eeg_filters/upload.py
eeg_filters-0.0.8.dist-info/LICENSE
eeg_filters-0.0.8.dist-info/METADATA
eeg_filters-0.0.8.dist-info/WHEEL
eeg_filters-0.0.8.dist-info/RECORD
