Metadata-Version: 2.3
Name: eeg-filters
Version: 0.0.8
Summary: Package for filtering EEG signals and EP (evoked potentials).
License: MIT
Author: Iaroslav Pisarev
Requires-Python: >=3.12,<4.0
Classifier: License :: OSI Approved :: MIT License
Classifier: Programming Language :: Python :: 3
Classifier: Programming Language :: Python :: 3.12
Classifier: Programming Language :: Python :: 3.13
Requires-Dist: loguru (>=0.7.3,<0.8.0)
Requires-Dist: matplotlib (>=3.10.1,<4.0.0)
Requires-Dist: numpy (>=2.2.4,<3.0.0)
Requires-Dist: pyedflib (>=0.1.40,<0.2.0)
Requires-Dist: scipy (>=1.15.2,<2.0.0)
